libname/__init__.py
libname/combination.py
combinationsum-0.0.1.dist-info/METADATA
combinationsum-0.0.1.dist-info/WHEEL
combinationsum-0.0.1.dist-info/top_level.txt
combinationsum-0.0.1.dist-info/RECORD
